mari-stubs/__init__.pyi
mari-stubs/current/__init__.pyi
mari-stubs/examples/__init__.pyi
mari-stubs/examples/action_manager.pyi
mari-stubs/examples/asset_management.pyi
mari-stubs/examples/c_api_channel_export.pyi
mari-stubs/examples/cameras.pyi
mari-stubs/examples/channels.pyi
mari-stubs/examples/colorspace.pyi
mari-stubs/examples/command_port.pyi
mari-stubs/examples/convert_channel.pyi
mari-stubs/examples/create_blacksmith_project.pyi
mari-stubs/examples/create_project.pyi
mari-stubs/examples/custom_layer.pyi
mari-stubs/examples/custom_shader.pyi
mari-stubs/examples/drag_and_drop_callbacks.pyi
mari-stubs/examples/export_dialog.pyi
mari-stubs/examples/export_shelf.pyi
mari-stubs/examples/filters.pyi
mari-stubs/examples/image_filters.pyi
mari-stubs/examples/layered_channels_for_layered_shaders.pyi
mari-stubs/examples/layered_channels_from_layered_shaders.pyi
mari-stubs/examples/layers.pyi
mari-stubs/examples/layers_NPMA_tiled_RGB.pyi
mari-stubs/examples/layers_disable_all_amount_values.pyi
mari-stubs/examples/lights.pyi
mari-stubs/examples/linked_patches.pyi
mari-stubs/examples/mGo.pyi
mari-stubs/examples/mGo_Materialiser.pyi
mari-stubs/examples/mGo_Shortcut_Actions.pyi
mari-stubs/examples/maya_export.pyi
mari-stubs/examples/nodes.pyi
mari-stubs/examples/paint_buffer.pyi
mari-stubs/examples/post_processing_filters.pyi
mari-stubs/examples/projectors.pyi
mari-stubs/examples/register_which_transforms.pyi
mari-stubs/examples/resource_info.pyi
mari-stubs/examples/selection_groups.pyi
mari-stubs/examples/shaders.pyi
mari-stubs/examples/shaderstacks.pyi
mari-stubs/examples/vector_brush.pyi
mari-stubs/examples/vector_channel.pyi
mari-stubs/py.typed
mari-stubs/session/__init__.pyi
mari-stubs/session/exceptions.pyi
mari-stubs/session/menu.pyi
mari-stubs/session/preferences.pyi
mari-stubs/session/types/__init__.pyi
mari-stubs/session/types/adjustable_layer.pyi
mari-stubs/session/types/adjustment_layer.pyi
mari-stubs/session/types/camera.pyi
types_mari-5.0.5.0.dist-info/METADATA
types_mari-5.0.5.0.dist-info/WHEEL
types_mari-5.0.5.0.dist-info/RECORD
